LICENSE
README.md
pyproject.toml
setup.cfg
setup.py
klyqa-home-assistant-integration/__init__.py
klyqa-home-assistant-integration/config_flow.py
klyqa-home-assistant-integration/const.py
klyqa-home-assistant-integration/light.py
klyqa-home-assistant-integration/vacuum.py
klyqa_ctl/__init__.py
klyqa_ctl/__main__.py
klyqa_ctl/account.py
klyqa_ctl/controller_data.py
klyqa_ctl/klyqa_ctl.py
klyqa_ctl/local_controller.py
klyqa_ctl.egg-info/PKG-INFO
klyqa_ctl.egg-info/SOURCES.txt
klyqa_ctl.egg-info/dependency_links.txt
klyqa_ctl.egg-info/entry_points.txt
klyqa_ctl.egg-info/requires.txt
klyqa_ctl.egg-info/top_level.txt
klyqa_ctl/communication/__init__.py
klyqa_ctl/communication/cloud.py
klyqa_ctl/communication/connection_handler.py
klyqa_ctl/communication/device_connection_handler.py
klyqa_ctl/communication/local/__init__.py
klyqa_ctl/communication/local/connection.py
klyqa_ctl/communication/local/connection_handler.py
klyqa_ctl/communication/local/data_package.py
klyqa_ctl/devices/__init__.py
klyqa_ctl/devices/commands.py
klyqa_ctl/devices/commands_device.py
klyqa_ctl/devices/connection.py
klyqa_ctl/devices/device.py
klyqa_ctl/devices/onboard.py
klyqa_ctl/devices/response_identity_message.py
klyqa_ctl/devices/response_message.py
klyqa_ctl/devices/group/__init__.py
klyqa_ctl/devices/light/__init__.py
klyqa_ctl/devices/light/commands.py
klyqa_ctl/devices/light/light.py
klyqa_ctl/devices/light/response_status.py
klyqa_ctl/devices/light/scenes.py
klyqa_ctl/devices/vacuum/__init__.py
klyqa_ctl/devices/vacuum/commands.py
klyqa_ctl/devices/vacuum/general.py
klyqa_ctl/devices/vacuum/response_status.py
klyqa_ctl/devices/vacuum/vacuum.py
klyqa_ctl/general/__init__.py
klyqa_ctl/general/general.py
klyqa_ctl/general/message.py
klyqa_ctl/general/parameters.py
klyqa_ctl/general/unit_id.py
test/__init__.py
test/conftest.py
test/load_test.py
test/test_account.py
test/test_cli.py
test/test_local_controller.py
test/test_local_controller_commands.py
test/test_message.py
test/test_send_msg.py