Metadata-Version: 2.1
Name: klyqa-ctl
Version: 1.0.19
Summary: A commandline client for controlling Klyqa smart devices
Home-page: https://github.com/klyqa/klyqa-ctl
Author: Frederick Stallmeyer
Author-email: fraizy@gmx.de
Maintainer: Frederick Stallmeyer <fraizy@gmx.de>
Maintainer-email: fraizy@gmx.de
License: MIT License
Project-URL: GitHub: issues, https://github.com/klyqa/klyqa-ctl/issues
Project-URL: GitHub: repo, https://github.com/klyqa/klyqa-ctl
Keywords: IoT,Klyqa,Smart,Qconnex,bulbs,lamps,vacuum,vc
Requires-Python: >=3.2
License-File: LICENSE
